{
    "copyright": "NHL and the NHL Shield are registered trademarks of the National Hockey League. NHL and NHL team marks are the property of the NHL and its teams. \u00a9 NHL 2023. All Rights Reserved.",
    "gamePk": 1975020501,
    "link": "/api/v1/game/1975020501/feed/live",
    "metaData": {
        "wait": 10,
        "timeStamp": "20170920_133042"
    },
    "gameData": {
        "game": {
            "pk": 1975020501,
            "season": "19751976",
            "type": "R"
        },
        "datetime": {
            "dateTime": "1976-02-14T04:00:00Z"
        },
        "status": {
            "abstractGameState": "Final",
            "codedGameState": "7",
            "detailedState": "Final",
            "statusCode": "7",
            "startTimeTBD": false
        },
        "teams": {
            "away": {
                "id": 6,
                "name": "Boston Bruins",
                "link": "/api/v1/teams/6",
                "venue": {
                    "id": 5085,
                    "name": "TD Garden",
                    "link": "/api/v1/venues/5085",
                    "city": "Boston",
                    "timeZone": {
                        "id": "America/New_York",
                        "offset": -4,
                        "tz": "EDT"
                    }
                },
                "abbreviation": "BOS",
                "triCode": "BOS",
                "teamName": "Bruins",
                "locationName": "Boston",
                "firstYearOfPlay": "1924",
                "division": {
                    "id": 11,
                    "name": "Adams",
                    "link": "/api/v1/divisions/11"
                },
                "conference": {
                    "id": 3,
                    "name": "Prince of Wales",
                    "link": "/api/v1/conferences/3"
                },
                "franchise": {
                    "franchiseId": 6,
                    "teamName": "Bruins",
                    "link": "/api/v1/franchises/6"
                },
                "shortName": "Boston",
                "officialSiteUrl": "http://www.bostonbruins.com",
                "franchiseId": 6,
                "active": true
            },
            "home": {
                "id": 56,
                "name": "California Golden Seals",
                "link": "/api/v1/teams/56",
                "abbreviation": "CGS",
                "triCode": "CGS",
                "teamName": "Golden Seals",
                "locationName": "California",
                "firstYearOfPlay": "1970",
                "division": {
                    "id": 11,
                    "name": "Adams",
                    "link": "/api/v1/divisions/11"
                },
                "conference": {
                    "id": 3,
                    "name": "Prince of Wales",
                    "link": "/api/v1/conferences/3"
                },
                "franchise": {
                    "franchiseId": 13,
                    "teamName": "Seals",
                    "link": "/api/v1/franchises/13"
                },
                "franchiseId": 13,
                "active": false
            }
        },
        "players": {
            "ID8448915": {
                "id": 8448915,
                "fullName": "Al MacAdam",
                "link": "/api/v1/people/8448915",
                "firstName": "Al",
                "lastName": "MacAdam",
                "primaryNumber": "25",
                "birthDate": "1952-03-16",
                "birthCity": "Charlottetown",
                "birthStateProvince": "PE",
                "birthCountry": "CAN",
                "nationality": "CAN",
                "active": false,
                "rookie": false,
                "rosterStatus": "N",
                "primaryPosition": {
                    "code": "R",
                    "name": "Right Wing",
                    "type": "Forward",
                    "abbreviation": "RW"
                }
            },
            "ID8451728": {
                "id": 8451728,
                "fullName": "Bob Stewart",
                "link": "/api/v1/people/8451728",
                "firstName": "Bob",
                "lastName": "Stewart",
                "primaryNumber": "4",
                "birthDate": "1950-11-10",
                "birthCity": "Charlottetown",
                "birthStateProvince": "PE",
                "birthCountry": "CAN",
                "nationality": "CAN",
                "active": false,
                "rookie": false,
                "rosterStatus": "N",
                "primaryPosition": {
                    "code": "D",
                    "name": "Defenseman",
                    "type": "Defenseman",
                    "abbreviation": "D"
                }
            },
            "ID8447905": {
                "id": 8447905,
                "fullName": "Jim Moxey",
                "link": "/api/v1/people/8447905",
                "firstName": "Jim",
                "lastName": "Moxey",
                "primaryNumber": "19",
                "birthDate": "1953-05-28",
                "birthCity": "Toronto",
                "birthStateProvince": "ON",
                "birthCountry": "CAN",
                "nationality": "CAN",
                "height": "6' 1\"",
                "weight": 190,
                "active": false,
                "rookie": false,
                "shootsCatches": "L",
                "rosterStatus": "N",
                "primaryPosition": {
                    "code": "R",
                    "name": "Right Wing",
                    "type": "Forward",
                    "abbreviation": "RW"
                }
            },
            "ID8451204": {
                "id": 8451204,
                "fullName": "Bobby Schmautz",
                "link": "/api/v1/people/8451204",
                "firstName": "Bobby",
                "lastName": "Schmautz",
                "primaryNumber": "19",
                "birthDate": "1945-03-28",
                "birthCity": "Saskatoon",
                "birthStateProvince": "SK",
                "birthCountry": "CAN",
                "nationality": "CAN",
                "active": false,
                "rookie": false,
                "rosterStatus": "N",
                "primaryPosition": {
                    "code": "R",
                    "name": "Right Wing",
                    "type": "Forward",
                    "abbreviation": "RW"
                }
            },
            "ID8450555": {
                "id": 8450555,
                "fullName": "Thomas Price",
                "link": "/api/v1/people/8450555",
                "firstName": "Thomas",
                "lastName": "Price",
                "primaryNumber": "25",
                "birthDate": "1954-07-12",
                "birthCity": "Toronto",
                "birthStateProvince": "ON",
                "birthCountry": "CAN",
                "nationality": "CAN",
                "active": false,
                "rookie": false,
                "rosterStatus": "N",
                "primaryPosition": {
                    "code": "D",
                    "name": "Defenseman",
                    "type": "Defenseman",
                    "abbreviation": "D"
                }
            },
            "ID8450114": {
                "id": 8450114,
                "fullName": "Gary Simmons",
                "link": "/api/v1/people/8450114",
                "firstName": "Gary",
                "lastName": "Simmons",
                "primaryNumber": "31",
                "birthDate": "1944-07-19",
                "birthCity": "Charlottetown",
                "birthStateProvince": "PE",
                "birthCountry": "CAN",
                "nationality": "CAN",
                "height": "6' 2\"",
                "weight": 200,
                "active": false,
                "rookie": false,
                "shootsCatches": "L",
                "rosterStatus": "N",
                "primaryPosition": {
                    "code": "G",
                    "name": "Goalie",
                    "type": "Goalie",
                    "abbreviation": "G"
                }
            },
            "ID8449672": {
                "id": 8449672,
                "fullName": "Joe Zanussi",
                "link": "/api/v1/people/8449672",
                "firstName": "Joe",
                "lastName": "Zanussi",
                "primaryNumber": "24",
                "birthDate": "1947-09-25",
                "birthCity": "Rossland",
                "birthStateProvince": "BC",
                "birthCountry": "CAN",
                "nationality": "CAN",
                "height": "5' 10\"",
                "weight": 180,
                "active": false,
                "rookie": false,
                "shootsCatches": "R",
                "rosterStatus": "N",
                "primaryPosition": {
                    "code": "D",
                    "name": "Defenseman",
                    "type": "Defenseman",
                    "abbreviation": "D"
                }
            },
            "ID8446560": {
                "id": 8446560,
                "fullName": "Darryl Edestrand",
                "link": "/api/v1/people/8446560",
                "firstName": "Darryl",
                "lastName": "Edestrand",
                "primaryNumber": "25",
                "birthDate": "1945-11-06",
                "birthCity": "Strathroy",
                "birthStateProvince": "ON",
                "birthCountry": "CAN",
                "nationality": "CAN",
                "height": "5' 11\"",
                "weight": 180,
                "active": false,
                "rookie": false,
                "shootsCatches": "L",
                "rosterStatus": "N",
                "primaryPosition": {
                    "code": "D",
                    "name": "Defenseman",
                    "type": "Defenseman",
                    "abbreviation": "D"
                }
            },
            "ID8447892": {
                "id": 8447892,
                "fullName": "Ken Hodge",
                "link": "/api/v1/people/8447892",
                "firstName": "Ken",
                "lastName": "Hodge",
                "primaryNumber": "88",
                "birthDate": "1944-06-25",
                "birthCity": "Birmingham",
                "birthCountry": "ENG",
                "nationality": "ENG",
                "height": "6' 2\"",
                "weight": 214,
                "active": false,
                "rookie": false,
                "shootsCatches": "R",
                "rosterStatus": "N",
                "primaryPosition": {
                    "code": "R",
                    "name": "Right Wing",
                    "type": "Forward",
                    "abbreviation": "RW"
                }
            },
            "ID8449570": {
                "id": 8449570,
                "fullName": "Wayne Merrick",
                "link": "/api/v1/people/8449570",
                "firstName": "Wayne",
                "lastName": "Merrick",
                "primaryNumber": "11",
                "birthDate": "1952-04-23",
                "birthCity": "Sarnia",
                "birthStateProvince": "ON",
                "birthCountry": "CAN",
                "nationality": "CAN",
                "active": false,
                "rookie": false,
                "rosterStatus": "N",
                "primaryPosition": {
                    "code": "C",
                    "name": "Center",
                    "type": "Forward",
                    "abbreviation": "C"
                }
            },
            "ID8447038": {
                "id": 8447038,
                "fullName": "Tim Jacobs",
                "link": "/api/v1/people/8447038",
                "firstName": "Tim",
                "lastName": "Jacobs",
                "primaryNumber": "23",
                "birthDate": "1952-03-28",
                "birthCity": "Espanola",
                "birthStateProvince": "ON",
                "birthCountry": "CAN",
                "nationality": "CAN",
                "height": "5' 10\"",
                "weight": 180,
                "active": false,
                "rookie": false,
                "shootsCatches": "L",
                "rosterStatus": "N",
                "primaryPosition": {
                    "code": "D",
                    "name": "Defenseman",
                    "type": "Defenseman",
                    "abbreviation": "D"
                }
            },
            "ID8449138": {
                "id": 8449138,
                "fullName": "Don Marcotte",
                "link": "/api/v1/people/8449138",
                "firstName": "Don",
                "lastName": "Marcotte",
                "primaryNumber": "21",
                "birthDate": "1947-04-15",
                "birthCity": "Asbestos",
                "birthStateProvince": "QC",
                "birthCountry": "CAN",
                "nationality": "CAN",
                "active": false,
                "rookie": false,
                "rosterStatus": "N",
                "primaryPosition": {
                    "code": "L",
                    "name": "Left Wing",
                    "type": "Forward",
                    "abbreviation": "LW"
                }
            },
            "ID8447157": {
                "id": 8447157,
                "fullName": "Doug Gibson",
                "link": "/api/v1/people/8447157",
                "firstName": "Doug",
                "lastName": "Gibson",
                "primaryNumber": "27",
                "birthDate": "1953-09-28",
                "birthCity": "Peterborough",
                "birthStateProvince": "ON",
                "birthCountry": "CAN",
                "nationality": "CAN",
                "height": "5' 10\"",
                "weight": 175,
                "active": false,
                "rookie": false,
                "shootsCatches": "L",
                "rosterStatus": "N",
                "primaryPosition": {
                    "code": "C",
                    "name": "Center",
                    "type": "Forward",
                    "abbreviation": "C"
                }
            },
            "ID8446002": {
                "id": 8446002,
                "fullName": "Wayne Cashman",
                "link": "/api/v1/people/8446002",
                "firstName": "Wayne",
                "lastName": "Cashman",
                "primaryNumber": "12",
                "birthDate": "1945-06-24",
                "birthCity": "Kingston",
                "birthStateProvince": "ON",
                "birthCountry": "CAN",
                "nationality": "CAN",
                "height": "6' 1\"",
                "weight": 208,
                "active": false,
                "rookie": false,
                "shootsCatches": "R",
                "rosterStatus": "N",
                "primaryPosition": {
                    "code": "L",
                    "name": "Left Wing",
                    "type": "Forward",
                    "abbreviation": "LW"
                }
            },
            "ID8447497": {
                "id": 8447497,
                "fullName": "Rick Hampton",
                "link": "/api/v1/people/8447497",
                "firstName": "Rick",
                "lastName": "Hampton",
                "primaryNumber": "2",
                "birthDate": "1956-06-14",
                "birthCity": "King",
                "birthStateProvince": "ON",
                "birthCountry": "CAN",
                "nationality": "CAN",
                "height": "6' 0\"",
                "weight": 190,
                "active": false,
                "rookie": false,
                "shootsCatches": "L",
                "rosterStatus": "N",
                "primaryPosition": {
                    "code": "D",
                    "name": "Defenseman",
                    "type": "Defenseman",
                    "abbreviation": "D"
                }
            },
            "ID8449737": {
                "id": 8449737,
                "fullName": "Bob Murdoch",
                "link": "/api/v1/people/8449737",
                "firstName": "Bob",
                "lastName": "Murdoch",
                "primaryNumber": "20",
                "birthDate": "1954-01-29",
                "birthCity": "Cranbrook",
                "birthStateProvince": "BC",
                "birthCountry": "CAN",
                "nationality": "CAN",
                "active": false,
                "rookie": false,
                "rosterStatus": "N",
                "primaryPosition": {
                    "code": "R",
                    "name": "Right Wing",
                    "type": "Forward",
                    "abbreviation": "RW"
                }
            },
            "ID8449853": {
                "id": 8449853,
                "fullName": "Gerry Cheevers",
                "link": "/api/v1/people/8449853",
                "firstName": "Gerry",
                "lastName": "Cheevers",
                "primaryNumber": "30",
                "birthDate": "1940-12-07",
                "birthCity": "St. Catharines",
                "birthStateProvince": "ON",
                "birthCountry": "CAN",
                "nationality": "CAN",
                "height": "5' 11\"",
                "weight": 185,
                "active": false,
                "rookie": false,
                "shootsCatches": "L",
                "rosterStatus": "N",
                "primaryPosition": {
                    "code": "G",
                    "name": "Goalie",
                    "type": "Goalie",
                    "abbreviation": "G"
                }
            },
            "ID8446588": {
                "id": 8446588,
                "fullName": "Bob Girard",
                "link": "/api/v1/people/8446588",
                "firstName": "Bob",
                "lastName": "Girard",
                "primaryNumber": "26",
                "birthDate": "1949-04-12",
                "birthCity": "Montreal",
                "birthStateProvince": "QC",
                "birthCountry": "CAN",
                "nationality": "CAN",
                "height": "6' 0\"",
                "weight": 180,
                "active": false,
                "rookie": false,
                "shootsCatches": "L",
                "rosterStatus": "N",
                "primaryPosition": {
                    "code": "L",
                    "name": "Left Wing",
                    "type": "Forward",
                    "abbreviation": "LW"
                }
            },
            "ID8446905": {
                "id": 8446905,
                "fullName": "Gary Holt",
                "link": "/api/v1/people/8446905",
                "firstName": "Gary",
                "lastName": "Holt",
                "primaryNumber": "21",
                "birthDate": "1952-01-01",
                "birthCity": "Sarnia",
                "birthStateProvince": "ON",
                "birthCountry": "CAN",
                "nationality": "CAN",
                "height": "5' 9\"",
                "weight": 175,
                "active": false,
                "rookie": false,
                "shootsCatches": "L",
                "rosterStatus": "N",
                "primaryPosition": {
                    "code": "L",
                    "name": "Left Wing",
                    "type": "Forward",
                    "abbreviation": "LW"
                }
            },
            "ID8450646": {
                "id": 8450646,
                "fullName": "Jean Ratelle",
                "link": "/api/v1/people/8450646",
                "firstName": "Jean",
                "lastName": "Ratelle",
                "primaryNumber": "19",
                "birthDate": "1940-10-03",
                "birthCity": "Lac St. Jean",
                "birthStateProvince": "QC",
                "birthCountry": "CAN",
                "nationality": "CAN",
                "height": "6' 1\"",
                "weight": 175,
                "active": false,
                "rookie": false,
                "rosterStatus": "N",
                "primaryPosition": {
                    "code": "C",
                    "name": "Center",
                    "type": "Forward",
                    "abbreviation": "C"
                }
            },
            "ID8446908": {
                "id": 8446908,
                "fullName": "Dave Forbes",
                "link": "/api/v1/people/8446908",
                "firstName": "Dave",
                "lastName": "Forbes",
                "primaryNumber": "14",
                "birthDate": "1948-11-16",
                "birthCity": "Montreal",
                "birthStateProvince": "QC",
                "birthCountry": "CAN",
                "nationality": "CAN",
                "height": "5' 10\"",
                "weight": 180,
                "active": false,
                "rookie": false,
                "shootsCatches": "L",
                "rosterStatus": "N",
                "primaryPosition": {
                    "code": "R",
                    "name": "Right Wing",
                    "type": "Forward",
                    "abbreviation": "RW"
                }
            },
            "ID8450206": {
                "id": 8450206,
                "fullName": "Brad Park",
                "link": "/api/v1/people/8450206",
                "firstName": "Brad",
                "lastName": "Park",
                "primaryNumber": "2",
                "birthDate": "1948-07-06",
                "birthCity": "Toronto",
                "birthStateProvince": "ON",
                "birthCountry": "CAN",
                "nationality": "CAN",
                "height": "6' 0\"",
                "weight": 200,
                "active": false,
                "rookie": false,
                "shootsCatches": "L",
                "rosterStatus": "N",
                "primaryPosition": {
                    "code": "D",
                    "name": "Defenseman",
                    "type": "Defenseman",
                    "abbreviation": "D"
                }
            },
            "ID8444908": {
                "id": 8444908,
                "fullName": "Fred Ahern",
                "link": "/api/v1/people/8444908",
                "firstName": "Fred",
                "lastName": "Ahern",
                "primaryNumber": "16",
                "birthDate": "1952-02-12",
                "birthCity": "Boston",
                "birthStateProvince": "MA",
                "birthCountry": "USA",
                "nationality": "USA",
                "height": "6' 0\"",
                "weight": 180,
                "active": false,
                "rookie": false,
                "shootsCatches": "R",
                "rosterStatus": "N",
                "primaryPosition": {
                    "code": "R",
                    "name": "Right Wing",
                    "type": "Forward",
                    "abbreviation": "RW"
                }
            },
            "ID8451335": {
                "id": 8451335,
                "fullName": "Gregg Sheppard",
                "link": "/api/v1/people/8451335",
                "firstName": "Gregg",
                "lastName": "Sheppard",
                "primaryNumber": "19",
                "birthDate": "1949-04-23",
                "birthCity": "North battleford",
                "birthStateProvince": "SK",
                "birthCountry": "CAN",
                "nationality": "CAN",
                "active": false,
                "rookie": false,
                "rosterStatus": "N",
                "primaryPosition": {
                    "code": "C",
                    "name": "Center",
                    "type": "Forward",
                    "abbreviation": "C"
                }
            },
            "ID8451144": {
                "id": 8451144,
                "fullName": "Andre Savard",
                "link": "/api/v1/people/8451144",
                "firstName": "Andre",
                "lastName": "Savard",
                "primaryNumber": "12",
                "birthDate": "1953-09-02",
                "birthCity": "Temiscamingue",
                "birthStateProvince": "QC",
                "birthCountry": "CAN",
                "nationality": "CAN",
                "active": false,
                "rookie": false,
                "rosterStatus": "N",
                "primaryPosition": {
                    "code": "C",
                    "name": "Center",
                    "type": "Forward",
                    "abbreviation": "C"
                }
            },
            "ID8450075": {
                "id": 8450075,
                "fullName": "Terry O'Reilly",
                "link": "/api/v1/people/8450075",
                "firstName": "Terry",
                "lastName": "O'Reilly",
                "primaryNumber": "24",
                "birthDate": "1951-06-07",
                "birthCity": "Niagara Falls",
                "birthStateProvince": "ON",
                "birthCountry": "CAN",
                "nationality": "CAN",
                "height": "6' 1\"",
                "weight": 200,
                "active": false,
                "rookie": false,
                "shootsCatches": "R",
                "rosterStatus": "N",
                "primaryPosition": {
                    "code": "R",
                    "name": "Right Wing",
                    "type": "Forward",
                    "abbreviation": "RW"
                }
            },
            "ID8449284": {
                "id": 8449284,
                "fullName": "Dennis Maruk",
                "link": "/api/v1/people/8449284",
                "firstName": "Dennis",
                "lastName": "Maruk",
                "primaryNumber": "21",
                "birthDate": "1955-11-17",
                "birthCity": "Toronto",
                "birthStateProvince": "ON",
                "birthCountry": "CAN",
                "nationality": "CAN",
                "active": false,
                "rookie": false,
                "rosterStatus": "N",
                "primaryPosition": {
                    "code": "C",
                    "name": "Center",
                    "type": "Forward",
                    "abbreviation": "C"
                }
            },
            "ID8445240": {
                "id": 8445240,
                "fullName": "Johnny Bucyk",
                "link": "/api/v1/people/8445240",
                "firstName": "Johnny",
                "lastName": "Bucyk",
                "primaryNumber": "9",
                "birthDate": "1935-05-12",
                "birthCity": "Edmonton",
                "birthStateProvince": "AB",
                "birthCountry": "CAN",
                "nationality": "CAN",
                "height": "6' 0\"",
                "weight": 215,
                "active": false,
                "rookie": false,
                "shootsCatches": "L",
                "rosterStatus": "N",
                "primaryPosition": {
                    "code": "L",
                    "name": "Left Wing",
                    "type": "Forward",
                    "abbreviation": "LW"
                }
            },
            "ID8448035": {
                "id": 8448035,
                "fullName": "Hank Nowak",
                "link": "/api/v1/people/8448035",
                "firstName": "Hank",
                "lastName": "Nowak",
                "primaryNumber": "18",
                "birthDate": "1950-11-24",
                "birthCity": "Oshawa",
                "birthStateProvince": "ON",
                "birthCountry": "CAN",
                "nationality": "CAN",
                "height": "6' 1\"",
                "weight": 195,
                "active": false,
                "rookie": false,
                "shootsCatches": "L",
                "rosterStatus": "N",
                "primaryPosition": {
                    "code": "L",
                    "name": "Left Wing",
                    "type": "Forward",
                    "abbreviation": "LW"
                }
            },
            "ID8449069": {
                "id": 8449069,
                "fullName": "Dallas Smith",
                "link": "/api/v1/people/8449069",
                "firstName": "Dallas",
                "lastName": "Smith",
                "primaryNumber": "15",
                "birthDate": "1941-10-10",
                "birthCity": "Hamiota",
                "birthStateProvince": "MB",
                "birthCountry": "CAN",
                "nationality": "CAN",
                "height": "5' 11\"",
                "weight": 180,
                "active": false,
                "rookie": false,
                "shootsCatches": "L",
                "rosterStatus": "N",
                "primaryPosition": {
                    "code": "D",
                    "name": "Defenseman",
                    "type": "Defenseman",
                    "abbreviation": "D"
                }
            },
            "ID8447042": {
                "id": 8447042,
                "fullName": "Dave Gardner",
                "link": "/api/v1/people/8447042",
                "firstName": "Dave",
                "lastName": "Gardner",
                "primaryNumber": "7",
                "birthDate": "1952-08-23",
                "birthCity": "Toronto",
                "birthStateProvince": "ON",
                "birthCountry": "CAN",
                "nationality": "CAN",
                "height": "6' 0\"",
                "weight": 185,
                "active": false,
                "rookie": false,
                "shootsCatches": "R",
                "rosterStatus": "N",
                "primaryPosition": {
                    "code": "C",
                    "name": "Center",
                    "type": "Forward",
                    "abbreviation": "C"
                }
            },
            "ID8446058": {
                "id": 8446058,
                "fullName": "Mike Christie",
                "link": "/api/v1/people/8446058",
                "firstName": "Mike",
                "lastName": "Christie",
                "primaryNumber": "3",
                "birthDate": "1949-12-20",
                "birthCity": "Big Spring",
                "birthStateProvince": "TX",
                "birthCountry": "USA",
                "nationality": "USA",
                "height": "6' 0\"",
                "weight": 190,
                "active": false,
                "rookie": false,
                "shootsCatches": "L",
                "rosterStatus": "N",
                "primaryPosition": {
                    "code": "D",
                    "name": "Defenseman",
                    "type": "Defenseman",
                    "abbreviation": "D"
                }
            },
            "ID8446976": {
                "id": 8446976,
                "fullName": "Len Frig",
                "link": "/api/v1/people/8446976",
                "firstName": "Len",
                "lastName": "Frig",
                "primaryNumber": "6",
                "birthDate": "1950-10-23",
                "birthCity": "Lethbridge",
                "birthStateProvince": "AB",
                "birthCountry": "CAN",
                "nationality": "CAN",
                "height": "5' 11\"",
                "weight": 190,
                "active": false,
                "rookie": false,
                "shootsCatches": "R",
                "rosterStatus": "N",
                "primaryPosition": {
                    "code": "D",
                    "name": "Defenseman",
                    "type": "Defenseman",
                    "abbreviation": "D"
                }
            },
            "ID8446434": {
                "id": 8446434,
                "fullName": "Gary Doak",
                "link": "/api/v1/people/8446434",
                "firstName": "Gary",
                "lastName": "Doak",
                "primaryNumber": "3",
                "birthDate": "1946-02-25",
                "birthCity": "Goderich",
                "birthStateProvince": "ON",
                "birthCountry": "CAN",
                "nationality": "CAN",
                "height": "5' 11\"",
                "weight": 175,
                "active": false,
                "rookie": false,
                "rosterStatus": "N",
                "primaryPosition": {
                    "code": "D",
                    "name": "Defenseman",
                    "type": "Defenseman",
                    "abbreviation": "D"
                }
            },
            "ID8448613": {
                "id": 8448613,
                "fullName": "Gary Sabourin",
                "link": "/api/v1/people/8448613",
                "firstName": "Gary",
                "lastName": "Sabourin",
                "primaryNumber": "11",
                "birthDate": "1943-12-04",
                "birthCity": "Parry Sound",
                "birthStateProvince": "ON",
                "birthCountry": "CAN",
                "nationality": "CAN",
                "height": "5' 11\"",
                "weight": 180,
                "active": false,
                "rookie": false,
                "shootsCatches": "R",
                "rosterStatus": "N",
                "primaryPosition": {
                    "code": "R",
                    "name": "Right Wing",
                    "type": "Forward",
                    "abbreviation": "RW"
                }
            }
        }
    },
    "liveData": {
        "plays": {
            "allPlays": [],
            "scoringPlays": [],
            "penaltyPlays": [],
            "playsByPeriod": []
        },
        "linescore": {
            "currentPeriod": 3,
            "currentPeriodOrdinal": "3rd",
            "currentPeriodTimeRemaining": "Final",
            "periods": [
                {
                    "periodType": "REGULAR",
                    "num": 1,
                    "ordinalNum": "1st",
                    "home": {
                        "goals": 2,
                        "shotsOnGoal": 0
                    },
                    "away": {
                        "goals": 2,
                        "shotsOnGoal": 0
                    }
                },
                {
                    "periodType": "REGULAR",
                    "num": 2,
                    "ordinalNum": "2nd",
                    "home": {
                        "goals": 1,
                        "shotsOnGoal": 0
                    },
                    "away": {
                        "goals": 1,
                        "shotsOnGoal": 0
                    }
                },
                {
                    "periodType": "REGULAR",
                    "num": 3,
                    "ordinalNum": "3rd",
                    "home": {
                        "goals": 2,
                        "shotsOnGoal": 0
                    },
                    "away": {
                        "goals": 3,
                        "shotsOnGoal": 0
                    }
                }
            ],
            "shootoutInfo": {
                "away": {
                    "scores": 0,
                    "attempts": 0
                },
                "home": {
                    "scores": 0,
                    "attempts": 0
                }
            },
            "teams": {
                "home": {
                    "team": {
                        "id": 56,
                        "name": "California Golden Seals",
                        "link": "/api/v1/teams/56",
                        "abbreviation": "CGS",
                        "triCode": "CGS"
                    },
                    "goals": 5,
                    "shotsOnGoal": 0,
                    "goaliePulled": false,
                    "numSkaters": 0,
                    "powerPlay": false
                },
                "away": {
                    "team": {
                        "id": 6,
                        "name": "Boston Bruins",
                        "link": "/api/v1/teams/6",
                        "abbreviation": "BOS",
                        "triCode": "BOS"
                    },
                    "goals": 6,
                    "shotsOnGoal": 0,
                    "goaliePulled": false,
                    "numSkaters": 0,
                    "powerPlay": false
                }
            },
            "powerPlayStrength": "Even",
            "hasShootout": false,
            "intermissionInfo": {
                "intermissionTimeRemaining": 0,
                "intermissionTimeElapsed": 0,
                "inIntermission": false
            }
        },
        "boxscore": {
            "teams": {
                "away": {
                    "team": {
                        "id": 6,
                        "name": "Boston Bruins",
                        "link": "/api/v1/teams/6",
                        "abbreviation": "BOS",
                        "triCode": "BOS"
                    },
                    "teamStats": {
                        "teamSkaterStats": {
                            "goals": 6,
                            "pim": 19,
                            "shots": 39,
                            "powerPlayGoals": 0.0
                        }
                    },
                    "players": {
                        "ID8450646": {
                            "person": {
                                "id": 8450646,
                                "fullName": "Jean Ratelle",
                                "link": "/api/v1/people/8450646",
                                "rosterStatus": "N"
                            },
                            "jerseyNumber": "10",
                            "position": {
                                "code": "C",
                                "name": "Center",
                                "type": "Forward",
                                "abbreviation": "C"
                            },
                            "stats": {
                                "skaterStats": {
                                    "timeOnIce": "00:00",
                                    "assists": 0,
                                    "goals": 0,
                                    "shots": 3,
                                    "powerPlayGoals": 0,
                                    "powerPlayAssists": 0,
                                    "penaltyMinutes": 0,
                                    "shortHandedGoals": 0,
                                    "shortHandedAssists": 0,
                                    "plusMinus": -1
                                }
                            }
                        },
                        "ID8446908": {
                            "person": {
                                "id": 8446908,
                                "fullName": "Dave Forbes",
                                "link": "/api/v1/people/8446908",
                                "shootsCatches": "L",
                                "rosterStatus": "N"
                            },
                            "jerseyNumber": "14",
                            "position": {
                                "code": "R",
                                "name": "Right Wing",
                                "type": "Forward",
                                "abbreviation": "RW"
                            },
                            "stats": {
                                "skaterStats": {
                                    "timeOnIce": "00:00",
                                    "assists": 2,
                                    "goals": 0,
                                    "shots": 4,
                                    "powerPlayGoals": 0,
                                    "powerPlayAssists": 0,
                                    "penaltyMinutes": 0,
                                    "shortHandedGoals": 0,
                                    "shortHandedAssists": 0,
                                    "plusMinus": 1
                                }
                            }
                        },
                        "ID8450206": {
                            "person": {
                                "id": 8450206,
                                "fullName": "Brad Park",
                                "link": "/api/v1/people/8450206",
                                "shootsCatches": "L",
                                "rosterStatus": "N"
                            },
                            "jerseyNumber": "22",
                            "position": {
                                "code": "D",
                                "name": "Defenseman",
                                "type": "Defenseman",
                                "abbreviation": "D"
                            },
                            "stats": {
                                "skaterStats": {
                                    "timeOnIce": "00:00",
                                    "assists": 2,
                                    "goals": 0,
                                    "shots": 3,
                                    "powerPlayGoals": 0,
                                    "powerPlayAssists": 0,
                                    "penaltyMinutes": 4,
                                    "shortHandedGoals": 0,
                                    "shortHandedAssists": 0,
                                    "plusMinus": 2
                                }
                            }
                        },
                        "ID8451335": {
                            "person": {
                                "id": 8451335,
                                "fullName": "Gregg Sheppard",
                                "link": "/api/v1/people/8451335",
                                "rosterStatus": "N"
                            },
                            "jerseyNumber": "19",
                            "position": {
                                "code": "C",
                                "name": "Center",
                                "type": "Forward",
                                "abbreviation": "C"
                            },
                            "stats": {
                                "skaterStats": {
                                    "timeOnIce": "00:00",
                                    "assists": 1,
                                    "goals": 1,
                                    "shots": 2,
                                    "powerPlayGoals": 0,
                                    "powerPlayAssists": 0,
                                    "penaltyMinutes": 0,
                                    "shortHandedGoals": 0,
                                    "shortHandedAssists": 0,
                                    "plusMinus": 2
                                }
                            }
                        },
                        "ID8451204": {
                            "person": {
                                "id": 8451204,
                                "fullName": "Bobby Schmautz",
                                "link": "/api/v1/people/8451204",
                                "rosterStatus": "N"
                            },
                            "jerseyNumber": "17",
                            "position": {
                                "code": "R",
                                "name": "Right Wing",
                                "type": "Forward",
                                "abbreviation": "RW"
                            },
                            "stats": {
                                "skaterStats": {
                                    "timeOnIce": "00:00",
                                    "assists": 0,
                                    "goals": 0,
                                    "shots": 5,
                                    "powerPlayGoals": 0,
                                    "powerPlayAssists": 0,
                                    "penaltyMinutes": 0,
                                    "shortHandedGoals": 0,
                                    "shortHandedAssists": 0,
                                    "plusMinus": -1
                                }
                            }
                        },
                        "ID8451144": {
                            "person": {
                                "id": 8451144,
                                "fullName": "Andre Savard",
                                "link": "/api/v1/people/8451144",
                                "rosterStatus": "N"
                            },
                            "jerseyNumber": "11",
                            "position": {
                                "code": "C",
                                "name": "Center",
                                "type": "Forward",
                                "abbreviation": "C"
                            },
                            "stats": {
                                "skaterStats": {
                                    "timeOnIce": "00:00",
                                    "assists": 0,
                                    "goals": 1,
                                    "shots": 4,
                                    "powerPlayGoals": 0,
                                    "powerPlayAssists": 0,
                                    "penaltyMinutes": 2,
                                    "shortHandedGoals": 0,
                                    "shortHandedAssists": 0,
                                    "plusMinus": -1
                                }
                            }
                        },
                        "ID8450075": {
                            "person": {
                                "id": 8450075,
                                "fullName": "Terry O'Reilly",
                                "link": "/api/v1/people/8450075",
                                "shootsCatches": "R",
                                "rosterStatus": "N"
                            },
                            "jerseyNumber": "24",
                            "position": {
                                "code": "R",
                                "name": "Right Wing",
                                "type": "Forward",
                                "abbreviation": "RW"
                            },
                            "stats": {
                                "skaterStats": {
                                    "timeOnIce": "00:00",
                                    "assists": 0,
                                    "goals": 0,
                                    "shots": 1,
                                    "powerPlayGoals": 0,
                                    "powerPlayAssists": 0,
                                    "penaltyMinutes": 0,
                                    "shortHandedGoals": 0,
                                    "shortHandedAssists": 0,
                                    "plusMinus": -1
                                }
                            }
                        },
                        "ID8449672": {
                            "person": {
                                "id": 8449672,
                                "fullName": "Joe Zanussi",
                                "link": "/api/v1/people/8449672",
                                "shootsCatches": "R",
                                "rosterStatus": "N"
                            },
                            "jerseyNumber": "29",
                            "position": {
                                "code": "D",
                                "name": "Defenseman",
                                "type": "Defenseman",
                                "abbreviation": "D"
                            },
                            "stats": {
                                "skaterStats": {
                                    "timeOnIce": "00:00",
                                    "assists": 0,
                                    "goals": 0,
                                    "shots": 0,
                                    "powerPlayGoals": 0,
                                    "powerPlayAssists": 0,
                                    "penaltyMinutes": 0,
                                    "shortHandedGoals": 0,
                                    "shortHandedAssists": 0,
                                    "plusMinus": 0
                                }
                            }
                        },
                        "ID8446560": {
                            "person": {
                                "id": 8446560,
                                "fullName": "Darryl Edestrand",
                                "link": "/api/v1/people/8446560",
                                "shootsCatches": "L",
                                "rosterStatus": "N"
                            },
                            "jerseyNumber": "6",
                            "position": {
                                "code": "D",
                                "name": "Defenseman",
                                "type": "Defenseman",
                                "abbreviation": "D"
                            },
                            "stats": {
                                "skaterStats": {
                                    "timeOnIce": "00:00",
                                    "assists": 1,
                                    "goals": 0,
                                    "shots": 0,
                                    "powerPlayGoals": 0,
                                    "powerPlayAssists": 0,
                                    "penaltyMinutes": 5,
                                    "shortHandedGoals": 0,
                                    "shortHandedAssists": 0,
                                    "plusMinus": 1
                                }
                            }
                        },
                        "ID8447892": {
                            "person": {
                                "id": 8447892,
                                "fullName": "Ken Hodge",
                                "link": "/api/v1/people/8447892",
                                "shootsCatches": "R",
                                "rosterStatus": "N"
                            },
                            "jerseyNumber": "8",
                            "position": {
                                "code": "R",
                                "name": "Right Wing",
                                "type": "Forward",
                                "abbreviation": "RW"
                            },
                            "stats": {
                                "skaterStats": {
                                    "timeOnIce": "00:00",
                                    "assists": 0,
                                    "goals": 0,
                                    "shots": 2,
                                    "powerPlayGoals": 0,
                                    "powerPlayAssists": 0,
                                    "penaltyMinutes": 0,
                                    "shortHandedGoals": 0,
                                    "shortHandedAssists": 0,
                                    "plusMinus": 0
                                }
                            }
                        },
                        "ID8445240": {
                            "person": {
                                "id": 8445240,
                                "fullName": "Johnny Bucyk",
                                "link": "/api/v1/people/8445240",
                                "shootsCatches": "L",
                                "rosterStatus": "N"
                            },
                            "jerseyNumber": "9",
                            "position": {
                                "code": "L",
                                "name": "Left Wing",
                                "type": "Forward",
                                "abbreviation": "LW"
                            },
                            "stats": {
                                "skaterStats": {
                                    "timeOnIce": "00:00",
                                    "assists": 0,
                                    "goals": 0,
                                    "shots": 1,
                                    "powerPlayGoals": 0,
                                    "powerPlayAssists": 0,
                                    "penaltyMinutes": 0,
                                    "shortHandedGoals": 0,
                                    "shortHandedAssists": 0,
                                    "plusMinus": 0
                                }
                            }
                        },
                        "ID8448035": {
                            "person": {
                                "id": 8448035,
                                "fullName": "Hank Nowak",
                                "link": "/api/v1/people/8448035",
                                "shootsCatches": "L",
                                "rosterStatus": "N"
                            },
                            "jerseyNumber": "18",
                            "position": {
                                "code": "L",
                                "name": "Left Wing",
                                "type": "Forward",
                                "abbreviation": "LW"
                            },
                            "stats": {
                                "skaterStats": {
                                    "timeOnIce": "00:00",
                                    "assists": 0,
                                    "goals": 0,
                                    "shots": 0,
                                    "powerPlayGoals": 0,
                                    "powerPlayAssists": 0,
                                    "penaltyMinutes": 0,
                                    "shortHandedGoals": 0,
                                    "shortHandedAssists": 0,
                                    "plusMinus": 2
                                }
                            }
                        },
                        "ID8449069": {
                            "person": {
                                "id": 8449069,
                                "fullName": "Dallas Smith",
                                "link": "/api/v1/people/8449069",
                                "shootsCatches": "L",
                                "rosterStatus": "N"
                            },
                            "jerseyNumber": "20",
                            "position": {
                                "code": "D",
                                "name": "Defenseman",
                                "type": "Defenseman",
                                "abbreviation": "D"
                            },
                            "stats": {
                                "skaterStats": {
                                    "timeOnIce": "00:00",
                                    "assists": 0,
                                    "goals": 0,
                                    "shots": 2,
                                    "powerPlayGoals": 0,
                                    "powerPlayAssists": 0,
                                    "penaltyMinutes": 2,
                                    "shortHandedGoals": 0,
                                    "shortHandedAssists": 0,
                                    "plusMinus": 1
                                }
                            }
                        },
                        "ID8449138": {
                            "person": {
                                "id": 8449138,
                                "fullName": "Don Marcotte",
                                "link": "/api/v1/people/8449138",
                                "rosterStatus": "N"
                            },
                            "jerseyNumber": "21",
                            "position": {
                                "code": "L",
                                "name": "Left Wing",
                                "type": "Forward",
                                "abbreviation": "LW"
                            },
                            "stats": {
                                "skaterStats": {
                                    "timeOnIce": "00:00",
                                    "assists": 0,
                                    "goals": 0,
                                    "shots": 0,
                                    "powerPlayGoals": 0,
                                    "powerPlayAssists": 0,
                                    "penaltyMinutes": 0,
                                    "shortHandedGoals": 0,
                                    "shortHandedAssists": 0,
                                    "plusMinus": 0
                                }
                            }
                        },
                        "ID8447157": {
                            "person": {
                                "id": 8447157,
                                "fullName": "Doug Gibson",
                                "link": "/api/v1/people/8447157",
                                "shootsCatches": "L",
                                "rosterStatus": "N"
                            },
                            "jerseyNumber": "27",
                            "position": {
                                "code": "C",
                                "name": "Center",
                                "type": "Forward",
                                "abbreviation": "C"
                            },
                            "stats": {
                                "skaterStats": {
                                    "timeOnIce": "00:00",
                                    "assists": 1,
                                    "goals": 2,
                                    "shots": 4,
                                    "powerPlayGoals": 0,
                                    "powerPlayAssists": 0,
                                    "penaltyMinutes": 0,
                                    "shortHandedGoals": 0,
                                    "shortHandedAssists": 0,
                                    "plusMinus": 3
                                }
                            }
                        },
                        "ID8446002": {
                            "person": {
                                "id": 8446002,
                                "fullName": "Wayne Cashman",
                                "link": "/api/v1/people/8446002",
                                "shootsCatches": "R",
                                "rosterStatus": "N"
                            },
                            "jerseyNumber": "12",
                            "position": {
                                "code": "L",
                                "name": "Left Wing",
                                "type": "Forward",
                                "abbreviation": "LW"
                            },
                            "stats": {
                                "skaterStats": {
                                    "timeOnIce": "00:00",
                                    "assists": 1,
                                    "goals": 2,
                                    "shots": 5,
                                    "powerPlayGoals": 0,
                                    "powerPlayAssists": 0,
                                    "penaltyMinutes": 4,
                                    "shortHandedGoals": 0,
                                    "shortHandedAssists": 0,
                                    "plusMinus": 4
                                }
                            }
                        },
                        "ID8446434": {
                            "person": {
                                "id": 8446434,
                                "fullName": "Gary Doak",
                                "link": "/api/v1/people/8446434",
                                "rosterStatus": "N"
                            },
                            "jerseyNumber": "25",
                            "position": {
                                "code": "D",
                                "name": "Defenseman",
                                "type": "Defenseman",
                                "abbreviation": "D"
                            },
                            "stats": {
                                "skaterStats": {
                                    "timeOnIce": "00:00",
                                    "assists": 1,
                                    "goals": 0,
                                    "shots": 3,
                                    "powerPlayGoals": 0,
                                    "powerPlayAssists": 0,
                                    "penaltyMinutes": 0,
                                    "shortHandedGoals": 0,
                                    "shortHandedAssists": 0,
                                    "plusMinus": 2
                                }
                            }
                        },
                        "ID8449853": {
                            "person": {
                                "id": 8449853,
                                "fullName": "Gerry Cheevers",
                                "link": "/api/v1/people/8449853",
                                "shootsCatches": "L",
                                "rosterStatus": "N"
                            },
                            "jerseyNumber": "31",
                            "position": {
                                "code": "G",
                                "name": "Goalie",
                                "type": "Goalie",
                                "abbreviation": "G"
                            },
                            "stats": {
                                "goalieStats": {
                                    "timeOnIce": "59:30",
                                    "assists": 0,
                                    "goals": 0,
                                    "pim": 2,
                                    "shots": 33,
                                    "saves": 28,
                                    "decision": "W",
                                    "savePercentage": 84.84848484848484
                                }
                            }
                        }
                    },
                    "goalies": [
                        8449853
                    ],
                    "skaters": [
                        8446560,
                        8447892,
                        8445240,
                        8450646,
                        8451144,
                        8446002,
                        8446908,
                        8451204,
                        8448035,
                        8451335,
                        8449069,
                        8449138,
                        8450206,
                        8450075,
                        8446434,
                        8447157,
                        8449672
                    ],
                    "onIce": [],
                    "onIcePlus": [],
                    "scratches": [],
                    "penaltyBox": [],
                    "coaches": []
                },
                "home": {
                    "team": {
                        "id": 56,
                        "name": "California Golden Seals",
                        "link": "/api/v1/teams/56",
                        "abbreviation": "CGS",
                        "triCode": "CGS"
                    },
                    "teamStats": {
                        "teamSkaterStats": {
                            "goals": 5,
                            "pim": 19,
                            "shots": 33,
                            "powerPlayGoals": 2.0
                        }
                    },
                    "players": {
                        "ID8448915": {
                            "person": {
                                "id": 8448915,
                                "fullName": "Al MacAdam",
                                "link": "/api/v1/people/8448915",
                                "rosterStatus": "N"
                            },
                            "jerseyNumber": "25",
                            "position": {
                                "code": "R",
                                "name": "Right Wing",
                                "type": "Forward",
                                "abbreviation": "RW"
                            },
                            "stats": {
                                "skaterStats": {
                                    "timeOnIce": "00:00",
                                    "assists": 0,
                                    "goals": 1,
                                    "shots": 1,
                                    "powerPlayGoals": 1,
                                    "powerPlayAssists": 0,
                                    "penaltyMinutes": 0,
                                    "shortHandedGoals": 0,
                                    "shortHandedAssists": 0,
                                    "plusMinus": -3
                                }
                            }
                        },
                        "ID8451728": {
                            "person": {
                                "id": 8451728,
                                "fullName": "Bob Stewart",
                                "link": "/api/v1/people/8451728",
                                "rosterStatus": "N"
                            },
                            "jerseyNumber": "4",
                            "position": {
                                "code": "D",
                                "name": "Defenseman",
                                "type": "Defenseman",
                                "abbreviation": "D"
                            },
                            "stats": {
                                "skaterStats": {
                                    "timeOnIce": "00:00",
                                    "assists": 1,
                                    "goals": 0,
                                    "shots": 2,
                                    "powerPlayGoals": 0,
                                    "powerPlayAssists": 0,
                                    "penaltyMinutes": 4,
                                    "shortHandedGoals": 0,
                                    "shortHandedAssists": 0,
                                    "plusMinus": -1
                                }
                            }
                        },
                        "ID8446905": {
                            "person": {
                                "id": 8446905,
                                "fullName": "Gary Holt",
                                "link": "/api/v1/people/8446905",
                                "shootsCatches": "L",
                                "rosterStatus": "N"
                            },
                            "jerseyNumber": "8",
                            "position": {
                                "code": "L",
                                "name": "Left Wing",
                                "type": "Forward",
                                "abbreviation": "LW"
                            },
                            "stats": {
                                "skaterStats": {
                                    "timeOnIce": "00:00",
                                    "assists": 0,
                                    "goals": 0,
                                    "shots": 0,
                                    "powerPlayGoals": 0,
                                    "powerPlayAssists": 0,
                                    "penaltyMinutes": 0,
                                    "shortHandedGoals": 0,
                                    "shortHandedAssists": 0,
                                    "plusMinus": 0
                                }
                            }
                        },
                        "ID8447905": {
                            "person": {
                                "id": 8447905,
                                "fullName": "Jim Moxey",
                                "link": "/api/v1/people/8447905",
                                "shootsCatches": "L",
                                "rosterStatus": "N"
                            },
                            "jerseyNumber": "19",
                            "position": {
                                "code": "R",
                                "name": "Right Wing",
                                "type": "Forward",
                                "abbreviation": "RW"
                            },
                            "stats": {
                                "skaterStats": {
                                    "timeOnIce": "00:00",
                                    "assists": 0,
                                    "goals": 1,
                                    "shots": 3,
                                    "powerPlayGoals": 0,
                                    "powerPlayAssists": 0,
                                    "penaltyMinutes": 0,
                                    "shortHandedGoals": 0,
                                    "shortHandedAssists": 0,
                                    "plusMinus": 1
                                }
                            }
                        },
                        "ID8444908": {
                            "person": {
                                "id": 8444908,
                                "fullName": "Fred Ahern",
                                "link": "/api/v1/people/8444908",
                                "shootsCatches": "R",
                                "rosterStatus": "N"
                            },
                            "jerseyNumber": "16",
                            "position": {
                                "code": "R",
                                "name": "Right Wing",
                                "type": "Forward",
                                "abbreviation": "RW"
                            },
                            "stats": {
                                "skaterStats": {
                                    "timeOnIce": "00:00",
                                    "assists": 1,
                                    "goals": 1,
                                    "shots": 5,
                                    "powerPlayGoals": 0,
                                    "powerPlayAssists": 0,
                                    "penaltyMinutes": 0,
                                    "shortHandedGoals": 0,
                                    "shortHandedAssists": 0,
                                    "plusMinus": 1
                                }
                            }
                        },
                        "ID8450555": {
                            "person": {
                                "id": 8450555,
                                "fullName": "Thomas Price",
                                "link": "/api/v1/people/8450555",
                                "rosterStatus": "N"
                            },
                            "jerseyNumber": "17",
                            "position": {
                                "code": "D",
                                "name": "Defenseman",
                                "type": "Defenseman",
                                "abbreviation": "D"
                            },
                            "stats": {
                                "skaterStats": {
                                    "timeOnIce": "00:00",
                                    "assists": 0,
                                    "goals": 0,
                                    "shots": 1,
                                    "powerPlayGoals": 0,
                                    "powerPlayAssists": 0,
                                    "penaltyMinutes": 0,
                                    "shortHandedGoals": 0,
                                    "shortHandedAssists": 0,
                                    "plusMinus": -1
                                }
                            }
                        },
                        "ID8450114": {
                            "person": {
                                "id": 8450114,
                                "fullName": "Gary Simmons",
                                "link": "/api/v1/people/8450114",
                                "shootsCatches": "L",
                                "rosterStatus": "N"
                            },
                            "jerseyNumber": "31",
                            "position": {
                                "code": "G",
                                "name": "Goalie",
                                "type": "Goalie",
                                "abbreviation": "G"
                            },
                            "stats": {
                                "goalieStats": {
                                    "timeOnIce": "60:00",
                                    "assists": 0,
                                    "goals": 0,
                                    "pim": 0,
                                    "shots": 39,
                                    "saves": 33,
                                    "decision": "L",
                                    "savePercentage": 84.61538461538461
                                }
                            }
                        },
                        "ID8449284": {
                            "person": {
                                "id": 8449284,
                                "fullName": "Dennis Maruk",
                                "link": "/api/v1/people/8449284",
                                "rosterStatus": "N"
                            },
                            "jerseyNumber": "21",
                            "position": {
                                "code": "C",
                                "name": "Center",
                                "type": "Forward",
                                "abbreviation": "C"
                            },
                            "stats": {
                                "skaterStats": {
                                    "timeOnIce": "00:00",
                                    "assists": 1,
                                    "goals": 0,
                                    "shots": 2,
                                    "powerPlayGoals": 0,
                                    "powerPlayAssists": 1,
                                    "penaltyMinutes": 4,
                                    "shortHandedGoals": 0,
                                    "shortHandedAssists": 0,
                                    "plusMinus": -3
                                }
                            }
                        },
                        "ID8449570": {
                            "person": {
                                "id": 8449570,
                                "fullName": "Wayne Merrick",
                                "link": "/api/v1/people/8449570",
                                "rosterStatus": "N"
                            },
                            "jerseyNumber": "9",
                            "position": {
                                "code": "C",
                                "name": "Center",
                                "type": "Forward",
                                "abbreviation": "C"
                            },
                            "stats": {
                                "skaterStats": {
                                    "timeOnIce": "00:00",
                                    "assists": 0,
                                    "goals": 1,
                                    "shots": 7,
                                    "powerPlayGoals": 0,
                                    "powerPlayAssists": 0,
                                    "penaltyMinutes": 0,
                                    "shortHandedGoals": 0,
                                    "shortHandedAssists": 0,
                                    "plusMinus": -1
                                }
                            }
                        },
                        "ID8447042": {
                            "person": {
                                "id": 8447042,
                                "fullName": "Dave Gardner",
                                "link": "/api/v1/people/8447042",
                                "shootsCatches": "R",
                                "rosterStatus": "N"
                            },
                            "jerseyNumber": "7",
                            "position": {
                                "code": "C",
                                "name": "Center",
                                "type": "Forward",
                                "abbreviation": "C"
                            },
                            "stats": {
                                "skaterStats": {
                                    "timeOnIce": "00:00",
                                    "assists": 3,
                                    "goals": 0,
                                    "shots": 3,
                                    "powerPlayGoals": 0,
                                    "powerPlayAssists": 1,
                                    "penaltyMinutes": 0,
                                    "shortHandedGoals": 0,
                                    "shortHandedAssists": 0,
                                    "plusMinus": 1
                                }
                            }
                        },
                        "ID8446058": {
                            "person": {
                                "id": 8446058,
                                "fullName": "Mike Christie",
                                "link": "/api/v1/people/8446058",
                                "shootsCatches": "L",
                                "rosterStatus": "N"
                            },
                            "jerseyNumber": "3",
                            "position": {
                                "code": "D",
                                "name": "Defenseman",
                                "type": "Defenseman",
                                "abbreviation": "D"
                            },
                            "stats": {
                                "skaterStats": {
                                    "timeOnIce": "00:00",
                                    "assists": 1,
                                    "goals": 0,
                                    "shots": 0,
                                    "powerPlayGoals": 0,
                                    "powerPlayAssists": 0,
                                    "penaltyMinutes": 4,
                                    "shortHandedGoals": 0,
                                    "shortHandedAssists": 0,
                                    "plusMinus": -1
                                }
                            }
                        },
                        "ID8447038": {
                            "person": {
                                "id": 8447038,
                                "fullName": "Tim Jacobs",
                                "link": "/api/v1/people/8447038",
                                "shootsCatches": "L",
                                "rosterStatus": "N"
                            },
                            "jerseyNumber": "23",
                            "position": {
                                "code": "D",
                                "name": "Defenseman",
                                "type": "Defenseman",
                                "abbreviation": "D"
                            },
                            "stats": {
                                "skaterStats": {
                                    "timeOnIce": "00:00",
                                    "assists": 1,
                                    "goals": 0,
                                    "shots": 1,
                                    "powerPlayGoals": 0,
                                    "powerPlayAssists": 1,
                                    "penaltyMinutes": 0,
                                    "shortHandedGoals": 0,
                                    "shortHandedAssists": 0,
                                    "plusMinus": -2
                                }
                            }
                        },
                        "ID8447497": {
                            "person": {
                                "id": 8447497,
                                "fullName": "Rick Hampton",
                                "link": "/api/v1/people/8447497",
                                "shootsCatches": "L",
                                "rosterStatus": "N"
                            },
                            "jerseyNumber": "2",
                            "position": {
                                "code": "D",
                                "name": "Defenseman",
                                "type": "Defenseman",
                                "abbreviation": "D"
                            },
                            "stats": {
                                "skaterStats": {
                                    "timeOnIce": "00:00",
                                    "assists": 0,
                                    "goals": 1,
                                    "shots": 2,
                                    "powerPlayGoals": 1,
                                    "powerPlayAssists": 0,
                                    "penaltyMinutes": 2,
                                    "shortHandedGoals": 0,
                                    "shortHandedAssists": 0,
                                    "plusMinus": -1
                                }
                            }
                        },
                        "ID8449737": {
                            "person": {
                                "id": 8449737,
                                "fullName": "Bob Murdoch",
                                "link": "/api/v1/people/8449737",
                                "rosterStatus": "N"
                            },
                            "jerseyNumber": "20",
                            "position": {
                                "code": "R",
                                "name": "Right Wing",
                                "type": "Forward",
                                "abbreviation": "RW"
                            },
                            "stats": {
                                "skaterStats": {
                                    "timeOnIce": "00:00",
                                    "assists": 1,
                                    "goals": 0,
                                    "shots": 0,
                                    "powerPlayGoals": 0,
                                    "powerPlayAssists": 1,
                                    "penaltyMinutes": 0,
                                    "shortHandedGoals": 0,
                                    "shortHandedAssists": 0,
                                    "plusMinus": -3
                                }
                            }
                        },
                        "ID8446976": {
                            "person": {
                                "id": 8446976,
                                "fullName": "Len Frig",
                                "link": "/api/v1/people/8446976",
                                "shootsCatches": "R",
                                "rosterStatus": "N"
                            },
                            "jerseyNumber": "6",
                            "position": {
                                "code": "D",
                                "name": "Defenseman",
                                "type": "Defenseman",
                                "abbreviation": "D"
                            },
                            "stats": {
                                "skaterStats": {
                                    "timeOnIce": "00:00",
                                    "assists": 0,
                                    "goals": 0,
                                    "shots": 1,
                                    "powerPlayGoals": 0,
                                    "powerPlayAssists": 0,
                                    "penaltyMinutes": 5,
                                    "shortHandedGoals": 0,
                                    "shortHandedAssists": 0,
                                    "plusMinus": 0
                                }
                            }
                        },
                        "ID8448613": {
                            "person": {
                                "id": 8448613,
                                "fullName": "Gary Sabourin",
                                "link": "/api/v1/people/8448613",
                                "shootsCatches": "R",
                                "rosterStatus": "N"
                            },
                            "jerseyNumber": "11",
                            "position": {
                                "code": "R",
                                "name": "Right Wing",
                                "type": "Forward",
                                "abbreviation": "RW"
                            },
                            "stats": {
                                "skaterStats": {
                                    "timeOnIce": "00:00",
                                    "assists": 0,
                                    "goals": 0,
                                    "shots": 3,
                                    "powerPlayGoals": 0,
                                    "powerPlayAssists": 0,
                                    "penaltyMinutes": 0,
                                    "shortHandedGoals": 0,
                                    "shortHandedAssists": 0,
                                    "plusMinus": 0
                                }
                            }
                        },
                        "ID8446588": {
                            "person": {
                                "id": 8446588,
                                "fullName": "Bob Girard",
                                "link": "/api/v1/people/8446588",
                                "shootsCatches": "L",
                                "rosterStatus": "N"
                            },
                            "jerseyNumber": "26",
                            "position": {
                                "code": "L",
                                "name": "Left Wing",
                                "type": "Forward",
                                "abbreviation": "LW"
                            },
                            "stats": {
                                "skaterStats": {
                                    "timeOnIce": "00:00",
                                    "assists": 1,
                                    "goals": 0,
                                    "shots": 2,
                                    "powerPlayGoals": 0,
                                    "powerPlayAssists": 0,
                                    "penaltyMinutes": 0,
                                    "shortHandedGoals": 0,
                                    "shortHandedAssists": 0,
                                    "plusMinus": -1
                                }
                            }
                        }
                    },
                    "goalies": [
                        8450114
                    ],
                    "skaters": [
                        8447497,
                        8446058,
                        8451728,
                        8446976,
                        8447042,
                        8446905,
                        8449570,
                        8448613,
                        8444908,
                        8450555,
                        8447905,
                        8449737,
                        8449284,
                        8447038,
                        8448915,
                        8446588
                    ],
                    "onIce": [],
                    "onIcePlus": [],
                    "scratches": [],
                    "penaltyBox": [],
                    "coaches": []
                }
            },
            "officials": [
                {
                    "official": {
                        "fullName": "Ron Wicks",
                        "link": "/api/v1/people/null"
                    },
                    "officialType": "Referee"
                },
                {
                    "official": {
                        "fullName": "Willard Norris",
                        "link": "/api/v1/people/null"
                    },
                    "officialType": "Linesman"
                },
                {
                    "official": {
                        "fullName": "Ray Scapinello",
                        "link": "/api/v1/people/null"
                    },
                    "officialType": "Linesman"
                }
            ]
        },
        "decisions": {
            "winner": {
                "id": 8449853,
                "fullName": "Gerry Cheevers",
                "link": "/api/v1/people/8449853"
            },
            "loser": {
                "id": 8450114,
                "fullName": "Gary Simmons",
                "link": "/api/v1/people/8450114"
            }
        }
    }
}